sun/__init__.py
sun/_utils.py
sun/application.py
sun/cache.py
sun/cache_memoize.py
sun/core.py
sun/decorators.py
sun/exceptions.py
sun/interceptors.py
sun/middlewares.py
sun/mixins.py
sun/paginate.py
sun/permissions.py
sun/routing.py
sun/schema.py
sun/tests.py
sun/aio/__init__.py
sun/aio/interceptors.py
sun/db/__init__.py
sun/db/comparators.py
sun/db/connection.py
sun/db/connection.pyi
sun/db/declarative.py
sun/db/models.py
sun/db/operators.py
sun/db/transaction.py
sun/events/__init__.py
sun/events/dispatch.py
sun/events/event.py
sun/events/handler.py
sun/resources/__init__.py
sun/resources/generic_routes.py
sun/resources/model_resource.py
sun/resources/resource.py
sun/rpc/__init__.py
sun/rpc/server.py
sun/schemas/__init__.py
sun/schemas/generic.py
sun/utils/__init__.py
sun/utils/dateparse.py
sun/utils/timezone.py
sun_core-0.1.7.dist-info/LICENSE
sun_core-0.1.7.dist-info/METADATA
sun_core-0.1.7.dist-info/WHEEL
sun_core-0.1.7.dist-info/top_level.txt
sun_core-0.1.7.dist-info/RECORD
