Metadata-Version: 2.1
Name: sun-core
Version: 0.1.7
Summary: 基于FastAPI和gRPC轻量级微服务开发框架
Home-page: https://github.com/xqk/sun
Author: xqk
Author-email: xiaqiankun@outlook.com
License: Apache License 2.0
Platform: UNKNOWN
License-File: LICENSE
Requires-Dist: aiomysql
Requires-Dist: aiosqlite
Requires-Dist: dateparser (>=1.1.0)
Requires-Dist: decamelize (==0.1.2)
Requires-Dist: fastapi[all] (<0.70,>=0.63.0)
Requires-Dist: fastapi-pagination (<0.9,>=0.7.4)
Requires-Dist: grpcio (<1.42,>=1.32.0)
Requires-Dist: grpcio-tools (<1.42,>=1.32.0)
Requires-Dist: grpc-interceptor (==0.13.0)
Requires-Dist: kombu (<6.0,>=5.2.4)
Requires-Dist: MarkupSafe (==2.0.1)
Requires-Dist: PyMySQL (<=0.9.3,>=0.9)
Requires-Dist: passlib[bcrypt] (==1.7.2)
Requires-Dist: pillow (>=7.2.0)
Requires-Dist: protobuf (<3.18,>=3.15)
Requires-Dist: pydantic-sqlalchemy (<1,>=0.0.7)
Requires-Dist: python-jose[cryptography] (==3.2.0)
Requires-Dist: pytz (==2021.1)
Requires-Dist: redis (==3.5.3)
Requires-Dist: regex (==2022.1.18)
Requires-Dist: sqla-wrapper (<5.6,>=5.0.0)
Requires-Dist: typer (>=0.4)
Requires-Dist: uvicorn (<=0.15,>=0.12.3)
Requires-Dist: etcd3 (==0.12.0)
